renconstruct/__init__.py
renconstruct/renconstruct.py
renconstruct/tasks/__init__.py
renconstruct/tasks/clean.py
renconstruct/tasks/keystore.py
renconstruct/tasks/largeaddress.py
renconstruct/tasks/notarize.py
renconstruct/tasks/patch.py
renconstruct-1.9.1.dist-info/entry_points.txt
renconstruct-1.9.1.dist-info/LICENSE
renconstruct-1.9.1.dist-info/WHEEL
renconstruct-1.9.1.dist-info/METADATA
renconstruct-1.9.1.dist-info/RECORD
