Metadata-Version: 2.1
Name: renconstruct
Version: 1.9.1
Summary: A utility script for automatically building Ren'Py applications for multiple platforms.
Home-page: https://github.com/kobaltcore/renconstruct
License: MIT
Author: CobaltCore
Author-email: cobaltcore@yandex.com
Requires-Python: >=3.7,<4.0
Classifier: License :: OSI Approved :: MIT License
Classifier: Programming Language :: Python :: 3
Classifier: Programming Language :: Python :: 3.10
Classifier: Programming Language :: Python :: 3.7
Classifier: Programming Language :: Python :: 3.8
Classifier: Programming Language :: Python :: 3.9
Requires-Dist: PyYAML (>=5.4.1,<6.0.0)
Requires-Dist: click (>=8.1.3,<9.0.0)
Requires-Dist: diff-match-patch (>=20200713,<20200714)
Requires-Dist: renotize (>=1.5.3,<2.0.0)
Requires-Dist: renutil (>=1.15.4,<2.0.0)
Requires-Dist: rich (>=10.16.2,<11.0.0)
Requires-Dist: termcolor (>=1.1.0,<2.0.0)
Requires-Dist: tqdm (>=4.64.0,<5.0.0)
Project-URL: Repository, https://github.com/kobaltcore/renconstruct
